{
  "item.contenttweaker.ticket": "Matter Ticket",
  "item.contenttweaker.ticket_catalyst": "Matter Ticket Catalyst",
  "item.contenttweaker.amc_crystal_submicroscopic": "Sub-microscopic Matter Crystal",
  "item.contenttweaker.amc_crystal_microscopic": "Microscopic Matter Crystal",
  "item.contenttweaker.amc_crystal_miniscule": "Miniscule Matter Crystal",
  "item.contenttweaker.amc_crystal_tiny": "Tiny Matter Crystal",
  "item.contenttweaker.amc_crystal_small": "Small Matter Crystal",
  "item.contenttweaker.amc_crystal_large": "Large Matter Crystal",
  "item.contenttweaker.alchemical_catalyst": "Alchemical Catalyst",
  "item.contenttweaker.advanced_alchemical_catalyst": "Advanced Alchemical Catalyst",
  "item.contenttweaker.very_advanced_alchemical_catalyst": "Very Advanced Alchemical Catalyst",
  "item.contenttweaker.alchemical_crystallization_catalyst": "Alchemical Crystallization Catalyst",
  "item.contenttweaker.alchemical_compression_catalyst": "Alchemical Compression Catalyst",
  "item.contenttweaker.alchemical_crystalpress_catalyst": "Alchemical Crystalpression Catalyst",
  "item.contenttweaker.token_catalyst": "Token Catalyst",
  "item.contenttweaker.advanced_token_catalyst": "Advanced Token Catalyst",
  "item.contenttweaker.very_advanced_token_catalyst": "Very Advanced Token Catalyst",
  "item.contenttweaker.highly_advanced_token_catalyst": "Highly Advanced Token Catalyst",
  "item.contenttweaker.alchemist_token_catalyst": "Alchemist's Advanced Token Catalyst",
  "item.contenttweaker.ashen_token": "Ashen Token",
  "item.contenttweaker.verdant_token": "Verdant Token",
  "item.contenttweaker.azure_token": "Azure Token",
  "item.contenttweaker.minium_token": "Minium Token",
  "item.contenttweaker.alchemist_token": "Alchemist's Token",
  "item.contenttweaker.bag": "Empty Alchemical Bag",
  "item.contenttweaker.1-bag": "Alchemical Bag (Holding 1 AMC)",
  "item.contenttweaker.2-bag": "Alchemical Bag (Holding 2 AMC)",
  "item.contenttweaker.5-bag": "Alchemical Bag (Holding 5 AMC)",
  "item.contenttweaker.10-bag": "Alchemical Bag (Holding 10 AMC)",
  "item.contenttweaker.25-bag": "Alchemical Bag (Holding 25 AMC)",
  "item.contenttweaker.50-bag": "Alchemical Bag (Holding 50 AMC)",
  "item.contenttweaker.100-bag": "Alchemical Bag (Holding 100 AMC)",
  "item.contenttweaker.crate": "Empty Alchemical Crate",
  "item.contenttweaker.250-crate": "Alchemical Crate (Storing 250 AMC)",
  "item.contenttweaker.500-crate": "Alchemical Crate (Storing 500 AMC)",
  "item.contenttweaker.1k-crate": "Alchemical Crate (Storing 1,000 AMC)",
  "item.contenttweaker.5k-crate": "Alchemical Crate (Storing 5,000 AMC)",
  "item.contenttweaker.10k-crate": "Alchemical Crate (Storing 10,000 AMC)",
  "item.contenttweaker.alchemical_sampling": "Alchemical Sampling",
  "item.contenttweaker.frozen_reagent": "Frozen Reagent"
}