{
	"conditions": [
		{
			"type": "forge:mod_loaded",
			"modid": "mobcompack"
		}
	],
    "entity": "mobcompack:crystallineslime",
    "name": "entity.mobcompack.crystallineslime",
    "name_color": "#751E35",
    "gui_scale": 1,
    "gui_x_offset": 0,
    "gui_y_offset": 0,
    "gui_z_offset": 0,
    "sim_cost": 192,
    "input": {
        "item": "hostilenetworks:prediction_matrix"
    },
    "base_drop": {
        "item": "hostilenetworks:nether_prediction"
    },
    "trivia": "custom.trivia.crystalline_slime",
    "fabricator_drops": [
        {
            "item": "mobcompack:rose_gelball",
            "count": 8
        },
        {
			"optional": true,
            "item": "biomesoplenty:rose_quartz_cluster",
            "count": 4
        }
    ]
}