{
	"name": "minerals",
	"icon": "alchemistry:mineral_salt",
	"color": "72dd5a",
	"decay": 0.75,
	"visible": true,
	"enabled": true,
	"food": {
		"oredict": [
			"cropStrawberry",
			"cropTomato",
			"listAllfruit"
		],
		"items": [
			"minecraft:fish",
			"minecraft:fish:1",
			"minecraft:fish:2",
			"minecraft:fish:3",
			"minecraft:cooked_fish",
			"minecraft:cooked_fish:1",
			"minecraft:beetroot",
			"minecraft:carrot",
			"minecraft:golden_carrot",
			"minecraft:melon",
			"minecraft:potato",
			"minecraft:baked_potato",
			"minecraft:mushroom_stew",
			"minecraft:beetroot_soup",
			"minecraft:milk_bucket",
			"minecraft:pumpkin_pie",
			"byg:goldenbeetroot",
			"byg:cookedcarrot",
			"byg:pumpkinmash",
			"byg:pumpkinbread",
			"byg:cookedpufferfish",
			"byg:cookedtropicalfish",
			"byg:carrotsoup",
			"byg:tropicalfishsoup",
			"byg:glowshroomsoupblue",
			"byg:green_glowshroom_stew",
			"byg:glowshroomsouppurple",
			"byg:cookedpumpkinseeds",
			"byg:rudobeansroasted",
			"byg:rudobeans",
			"glacidus:grape_juice",
			"glacidus:raisins",
			"glacidus:raw_porcali_meat",
			"glacidus:grilled_porcali_meat",
			"natura:edibles:1",
			"natura:soups",
			"natura:soups:1",
			"natura:soups:2",
			"natura:soups:3",
			"natura:soups:4",
			"natura:soups:5",
			"natura:soups:6",
			"natura:soups:7",
			"natura:soups:8",
			"natura:soups:9",
			"openblocks:tasty_clay",
			"rewired:powerbar",
			"rewired:energydrink",
			"xlfoodmod:bourbon_biscuit",
			"xlfoodmod:breakfast_sandwich",
			"xlfoodmod:brownie",
			"xlfoodmod:butter",
			"xlfoodmod:butter_rice",
			"xlfoodmod:caesar_salad",
			"xlfoodmod:cheese",
			"xlfoodmod:cheese_pie",
			"xlfoodmod:cheese_puff",
			"xlfoodmod:cheeseburger",
			"xlfoodmod:cheesy_bread",
			"xlfoodmod:chicken_salad",
			"xlfoodmod:chocolate",
			"xlfoodmod:chocolate_icecream",
			"xlfoodmod:corn_bread",
			"xlfoodmod:crouton",
			"xlfoodmod:fish_pie",
			"xlfoodmod:fried_egg",
			"xlfoodmod:golden_apple_pie",	
			"xlfoodmod:grilled_cheese_sandwich",
			"xlfoodmod:icecream_sandwich",
			"xlfoodmod:jambon_beurre",
			"xlfoodmod:macaroni_and_cheese",
			"xlfoodmod:onion",
			"xlfoodmod:onion_rings",
			"xlfoodmod:onion_salad",
			"xlfoodmod:pepper",
			"xlfoodmod:potato_bread",
			"xlfoodmod:pumpkin_bread",
			"xlfoodmod:pumpkin_cake",
			"xlfoodmod:pumpkin_stew",
			"xlfoodmod:rice_bread",
			"xlfoodmod:strawberry_icecream",
			"xlfoodmod:tomato_soup",
			"xlfoodmod:vanilla_icecream",
			"xlfoodmod:vegetable_soup"
		]
	}
}