{
  "name": "compactmachines3:generator_ender",
  "target-block": "extrautils2:machine",
  "target-nbt": "{Type:\"extrautils2:generator_ender\"}",
  "target-count": 1,
  "catalyst": "extrautils2:machine",
  "catalyst-nbt": "{Type:\"extrautils2:generator\"}",
  "duration": 300,
  
  "input-types": {
	"r": {"id": "minecraft:redstone_wire"},
	"p": {"id": "additionalcompression:pearlender_compressed"}
  },

  "symmetrical": true,
  "shape": [
	[
      ["r", "r", "r"],
      ["r", "p", "r"],
      ["r", "r", "r"]
	]
  ]
}